Workbook

Sheet All Active Projects
A1: Northstar Heritage, LLC
A2: FP&A & QC Project Report
A3: As of September 29, 2026
G8: Contract Value | H8: Revenue | I8: Invoiced Amount | J8: Total Revised Budget | K8: Total Budget | L8: Total Budget Adjustment | M8: Total Costs | Q8: Recognized %
G9: Inception To Date | H9: Inception To Date | I9: Inception To Date | J9: Orig Budget + Adjustments | K9: Original | L9: ETC | M9: Inception To Date | N9: Remaining Budget | O9: Orig Budget Remaining | Q9: REV REC % | R9: Budget Spent %
A11: Project ID | B11: Dimension name | C11: Project status | D11: Project Billing type | E11: Location Name | F11: Project Manager Name | G11: EOP | H11: Actual | I11: Actual | J11: Actual | K11: Actual | L11: Actual | M11: Actual | N11: Remaining Budget | O11: Original Budget Remaining | P11: teamwork Status | Q11: Actual | R11: Summary
A12: 23-PC-30307 | B12: Quail Run Wastewater Plant Cultural Resources Assessment | C12: Transferred Entity | D12: Fixed fee | E12: Big Sky | F12: Javier Estrada | G12: 240100 | H12: 157553.62 | I12: 157553.62 | J12: 136256.75 | K12: 136256.75 | L12: 0 | M12: 89412.87 | N12: 46843.88 | O12: 46843.88 | Q12: 0.656 | R12: 0.6562
A13: 23-PC-30372 | B13: Phase I: Lone Pine Reservoir Architectural History Survey | C13: In Progress | D13: Time and material | E13: Big Sky | F13: Bob Frye | G13: 27100 | H13: 18428 | I13: 18428 | J13: 19864.3 | K13: 19864.3 | L13: 0 | M13: 11402.28 | N13: 8462.02 | O13: 8462.02 | Q13: 0.68 | R13: 0.574
A14: 23-PC-30543 | B14: Phase III: Riverbend Rail Siding Maritime Remote Sensing Survey | C14: In Progress | D14: Fixed fee | E14: Big Sky | F14: Javier Estrada | G14: 320600 | H14: 225766.52 | I14: 225766.52 | J14: 255628.66 | K14: 192683.15 | L14: 62945.51 | M14: 180013.95 | N14: 75614.71 | O14: 12669.2 | Q14: 0.704 | R14: 0.7042
A15: 23-PC-30644 | B15: Phase II: Millbrook Wastewater Plant Data Recovery | C15: In Progress | D15: Time and material | E15: Bluegrass | F15: Alice Galloway | G15: 108100 | H15: 73508 | I15: 73508 | J15: 72102.7 | K15: 72102.7 | L15: 0 | M15: 46653.03 | N15: 25449.67 | O15: 25449.67 | Q15: 0.68 | R15: 0.647
A16: 23-PC-30869 | B16: Lone Pine Housing Development - Paleontological Monitoring | C16: In Progress | D16: Time and material | E16: Bluegrass | F16: Kiara Gillespie | G16: 49800 | H16: 33864 | I16: 33864 | J16: 34501.44 | K16: 34501.44 | L16: 0 | M16: 28656.36 | N16: 5845.08 | O16: 5845.08 | Q16: 0.68 | R16: 0.8306
A17: 23-PC-30881 | B17: Dove Canyon Mixed-Use Development Archaeological Testing | C17: Cost Tracking on Closed Project | D17: Time and material | E17: Bluegrass | F17: Alice Galloway | G17: 86200 | H17: 58616 | I17: 58616 | J17: 58650.48 | K17: 58650.48 | L17: 0 | M17: 61318.15 | N17: -2667.67 | O17: -2667.67 | Q17: 0.68 | R17: 1.0455
A18: 23-PC-31003 | B18: Windmill Flat Environmental Review Support | C18: In Progress | D18: Fixed fee | E18: Bluegrass | F18: Kiara Gillespie | G18: 19300 | H18: 15445.79 | I18: 15445.79 | J18: 10568.68 | K18: 10568.68 | L18: 0 | M18: 8458.51 | N18: 2110.17 | O18: 2110.17 | Q18: 0.8 | R18: 0.8003
A19: 23-PC-31042 | B19: Stone Mill Historic Resources Evaluation | C19: In Progress | D19: Time and material | E19: Cascade | F19: Donald Lutz | G19: 299700 | H19: 203796 | I19: 203796 | J19: 202896.9 | K19: 202896.9 | L19: 0 | M19: 147919.88 | N19: 54977.02 | O19: 54977.02 | Q19: 0.68 | R19: 0.729
A20: 23-PC-31076 | B20: Wildrye Rail Siding - Archaeological Testing | C20: Final Reporting/Review | D20: Time and material | E20: Cascade | F20: Cassidy Gay | G20: 95100 | H20: 64668 | I20: 64668 | J20: 65561.94 | K20: 65561.94 | L20: 0 | M20: 41531.43 | N20: 24030.51 | O20: 24030.51 | Q20: 0.68 | R20: 0.6335
A21: 23-PC-31344 | B21: Timber Gap Battery Storage Archaeological Testing | C21: In Progress | D21: Fixed fee | E21: Cascade | F21: Cassidy Gay | G21: 331600 | H21: 194516.56 | I21: 194516.56 | J21: 264351.52 | K21: 264351.52 | L21: 0 | M21: 155057.32 | N21: 109294.2 | O21: 109294.2 | Q21: 0.587 | R21: 0.5866
A22: 23-PC-31374 | B22: Juniper Wash Canal Lining Environmental Review Support | C22: In Progress | D22: Time and material | E22: Cascade | F22: Donald Lutz | G22: 255700 | H22: 173876 | I22: 173876 | J22: 168225.03 | K22: 168225.03 | L22: 0 | M22: 202903.45 | N22: -34678.42 | O22: -34678.42 | Q22: 0.68 | R22: 1.2061
A23: 23-PC-31405 | B23: Phase II: Maple Fork Mixed-Use Development Built Environment Survey | C23: In Progress | D23: Fixed fee | E23: Cascade | F23: Jeff Spence | G23: 108000 | H23: 76528.8 | I23: 76528.8 | J23: 82404 | K23: 82404 | L23: 0 | M23: 58391.35 | N23: 24012.65 | O23: 24012.65 | Q23: 0.709 | R23: 0.7086
... A869: 25-PC-44140 | B869: Stone Mill Archaeological Testing | C869: In Progress | D869: Fixed fee | E869: NH Gulf | F869: Tonya Spence | G869: 149900 | H869: 149510.26 | I869: 130809.05 | J869: 100298.09 | K869: 100298.09 | L869: 0 | M869: 100035.45 | N869: 262.63733 | O869: 262.63733 | Q869: 0.99739999 | R869: 0.99738143

Sheet Projects >70% Exec View
D1: Summary:
D2: Removed projects with ETC>1% budget remaining
D3: Removed $0 Contract Value projects
D4: Removed previously identified ETC in final/reportingstatus
D5: Removed projects in final reporting with >10% budget remaining
D6: Total: 273
F8: Contract Value | G8: Total Revised Budget | H8: Original Budget | I8: ETC | J8: Revenue Recognized | K8: Rev Rec % | L8: Cost | M8: Budget Remaining | N8: Budget Spent % | O8: Project Gross Profit
F9: September 29, 2026 | G9: September 29, 2026 | H9: September 29, 2026 | I9: September 29, 2026 | J9: September 29, 2026 | K9: September 29, 2026 | L9: September 29, 2026 | M9: September 29, 2026 | N9: September 29, 2026 | O9: September 29, 2026
A10: Project ID | B10: Project Name | C10: Project Billing type | D10: Project status | E10: Project Manager Name | F10: Actual | G10: Actual | H10: Actual | I10: Actual | J10: Actual | K10: Actual | L10: Actual | M10: Actual | N10: Actual | O10: Actual | P10: Location Name
A11: 23-PC-30869 | B11: Lone Pine Housing Development - Paleontological Monitoring | C11: Time and material | D11: In Progress | E11: Kiara Gillespie | F11: 49800 | G11: 34501.44 | H11: 34501.44 | I11: 0 | J11: 33864 | K11: 0.68 | L11: 28656.36 | M11: 5845.08 | N11: =IF(G11=0,0,L11/G11) | O11: =J11-L11 | P11: Bluegrass
A12: 23-PC-30881 | B12: Dove Canyon Mixed-Use Development Archaeological Testing | C12: Time and material | D12: Cost Tracking on Closed Project | E12: Alice Galloway | F12: 86200 | G12: 58650.48 | H12: 58650.48 | I12: 0 | J12: 58616 | K12: 0.68 | L12: 61318.15 | M12: -2667.67 | N12: =IF(G12=0,0,L12/G12) | O12: =J12-L12 | P12: Bluegrass
A13: 23-PC-31003 | B13: Windmill Flat Environmental Review Support | C13: Fixed fee | D13: In Progress | E13: Kiara Gillespie | F13: 19300 | G13: 10568.68 | H13: 10568.68 | I13: 0 | J13: 15445.79 | K13: 0.8 | L13: 8458.51 | M13: 2110.17 | N13: =IF(G13=0,0,L13/G13) | O13: =J13-L13 | P13: Bluegrass
A14: 23-PC-31042 | B14: Stone Mill Historic Resources Evaluation | C14: Time and material | D14: In Progress | E14: Donald Lutz | F14: 299700 | G14: 202896.9 | H14: 202896.9 | I14: 0 | J14: 203796 | K14: 0.68 | L14: 147919.88 | M14: 54977.02 | N14: =IF(G14=0,0,L14/G14) | O14: =J14-L14 | P14: Cascade
A15: 23-PC-31374 | B15: Juniper Wash Canal Lining Environmental Review Support | C15: Time and material | D15: In Progress | E15: Donald Lutz | F15: 255700 | G15: 168225.03 | H15: 168225.03 | I15: 0 | J15: 173876 | K15: 0.68 | L15: 202903.45 | M15: -34678.42 | N15: =IF(G15=0,0,L15/G15) | O15: =J15-L15 | P15: Cascade
A16: 23-PC-31405 | B16: Phase II: Maple Fork Mixed-Use Development Built Environment Survey | C16: Fixed fee | D16: In Progress | E16: Jeff Spence | F16: 108000 | G16: 82404 | H16: 82404 | I16: 0 | J16: 76528.8 | K16: 0.709 | L16: 58391.35 | M16: 24012.65 | N16: =IF(G16=0,0,L16/G16) | O16: =J16-L16 | P16: Cascade
A17: 23-PC-31769 | B17: Rushgrass Draw Paleontological Monitoring | C17: Fixed fee | D17: In Progress | E17: Gene Nixon | F17: 34800 | G17: 28779.6 | H17: 28779.6 | I17: 0 | J17: 34800 | K17: 1 | L17: 31540.76 | M17: -2761.16 | N17: =IF(G17=0,0,L17/G17) | O17: =J17-L17 | P17: Cascade
A18: 23-PC-31812 | B18: On-Call: Granite Pass Mine Expansion Phase II Testing | C18: Fixed fee | D18: In Progress | E18: Jeff Spence | F18: 460600 | G18: 390957.28 | H18: 390957.28 | I18: 0 | J18: 348674.2 | K18: 0.757 | L18: 295973.9 | M18: 94983.38 | N18: =IF(G18=0,0,L18/G18) | O18: =J18-L18 | P18: Cascade
A19: 23-PC-31844 | B19: Task Order 37: Sea Oat Water Main Archaeological Testing | C19: Fixed fee | D19: Cost Tracking on Closed Project | E19: Jeff Spence | F19: 175300 | G19: 93481.01 | H19: 71376.84 | I19: 22104.17 | J19: 175300 | K19: 1 | L19: 112759.17 | M19: -19278.16 | N19: =IF(G19=0,0,L19/G19) | O19: =J19-L19 | P19: Cascade
A20: 23-PC-32329 | B20: Rushgrass Draw Historic Resources Evaluation | C20: Fixed fee | D20: In Progress | E20: Sandy Kerr | F20: 149100 | G20: 111109.32 | H20: 111109.32 | I20: 0 | J20: 132892.83 | K20: 0.891 | L20: 99032.78 | M20: 12076.54 | N20: =IF(G20=0,0,L20/G20) | O20: =J20-L20 | P20: Chesapeake
A21: 23-PC-32635 | B21: Rushgrass Draw Curation | C21: Time and material | D21: Cost Tracking on Closed Project | E21: Jason Oconnor | F21: 36800 | G21: 24644.96 | H21: 24644.96 | I21: 0 | J21: 25024 | K21: 0.68 | L21: 27323.95 | M21: -2678.99 | N21: =IF(G21=0,0,L21/G21) | O21: =J21-L21 | P21: Chesapeake
A22: 23-PC-33070 | B22: Meadowlark Curation | C22: Fixed fee | D22: In Progress | E22: Reginald Vargas | F22: 55100 | G22: 34299.75 | H22: 34299.75 | I22: 0 | J22: 46377.67 | K22: 0.842 | L22: 28871.53 | M22: 5428.22 | N22: =IF(G22=0,0,L22/G22) | O22: =J22-L22 | P22: Front Range
... A283: 25-PC-44140 | B283: Stone Mill Archaeological Testing | C283: Fixed fee | D283: In Progress | E283: Tonya Spence | F283: 149900 | G283: 100298.09 | H283: 100298.09 | I283: 0 | J283: 149510.26 | K283: 0.99739999 | L283: 100035.45 | M283: 262.63733 | N283: =IF(G283=0,0,L283/G283) | O283: =J283-L283 | P283: NH Gulf

Sheet Projects >70% 
D1: Summary:
D2: Removed projects with ETC>1% budget remaining
D3: Removed $0 Contract Value projects
D4: Removed previously identified ETC in final/reportingstatus
D5: Removed projects in final reporting with >10% budget remaining
D6: Total: 273
G8: Contract Value | H8: Revenue | I8: Invoiced Amount | J8: Total Revised Budget | K8: Total Budget | L8: Total Budget Adjustment | M8: Total Costs | O8: Recognized %
G9: Inception To Date | H9: Inception To Date | I9: Inception To Date | J9: Orig Budget + Adjustments | K9: Original | L9: ETC | M9: Inception To Date | N9: Inception To Date | O9: REV REC % | P9: Budget Spent %
G10: September 29, 2026 | H10: September 29, 2026 | I10: September 29, 2026 | J10: September 29, 2026 | K10: September 29, 2026 | L10: September 29, 2026 | M10: September 29, 2026 | N10: September 29, 2026 | O10: September 29, 2026
B11: Dimension name | C11: Project status | D11: Project Billing type | E11: Location Name | F11: Project Manager Name | G11: EOP | H11: Actual | I11: Actual | J11: Actual | K11: Actual | L11: Actual | M11: Actual | N11: Remaining Budget | O11: Actual | P11: Summary
A12: 23-PC-30869 | B12: Lone Pine Housing Development - Paleontological Monitoring | C12: In Progress | D12: Time and material | E12: Bluegrass | F12: Kiara Gillespie | G12: 49800 | H12: 33864 | I12: 33864 | J12: 34501.44 | K12: 34501.44 | L12: 0 | M12: 28656.36 | N12: 5845.08 | O12: 0.68 | P12: 0.8306
A13: 23-PC-30881 | B13: Dove Canyon Mixed-Use Development Archaeological Testing | C13: Cost Tracking on Closed Project | D13: Time and material | E13: Bluegrass | F13: Alice Galloway | G13: 86200 | H13: 58616 | I13: 58616 | J13: 58650.48 | K13: 58650.48 | L13: 0 | M13: 61318.15 | N13: -2667.67 | O13: 0.68 | P13: 1.0455
A14: 23-PC-31003 | B14: Windmill Flat Environmental Review Support | C14: In Progress | D14: Fixed fee | E14: Bluegrass | F14: Kiara Gillespie | G14: 19300 | H14: 15445.79 | I14: 15445.79 | J14: 10568.68 | K14: 10568.68 | L14: 0 | M14: 8458.51 | N14: 2110.17 | O14: 0.8 | P14: 0.8003
A15: 23-PC-31042 | B15: Stone Mill Historic Resources Evaluation | C15: In Progress | D15: Time and material | E15: Cascade | F15: Donald Lutz | G15: 299700 | H15: 203796 | I15: 203796 | J15: 202896.9 | K15: 202896.9 | L15: 0 | M15: 147919.88 | N15: 54977.02 | O15: 0.68 | P15: 0.729
A16: 23-PC-31374 | B16: Juniper Wash Canal Lining Environmental Review Support | C16: In Progress | D16: Time and material | E16: Cascade | F16: Donald Lutz | G16: 255700 | H16: 173876 | I16: 173876 | J16: 168225.03 | K16: 168225.03 | L16: 0 | M16: 202903.45 | N16: -34678.42 | O16: 0.68 | P16: 1.2061
A17: 23-PC-31405 | B17: Phase II: Maple Fork Mixed-Use Development Built Environment Survey | C17: In Progress | D17: Fixed fee | E17: Cascade | F17: Jeff Spence | G17: 108000 | H17: 76528.8 | I17: 76528.8 | J17: 82404 | K17: 82404 | L17: 0 | M17: 58391.35 | N17: 24012.65 | O17: 0.709 | P17: 0.7086
A18: 23-PC-31769 | B18: Rushgrass Draw Paleontological Monitoring | C18: In Progress | D18: Fixed fee | E18: Cascade | F18: Gene Nixon | G18: 34800 | H18: 34800 | I18: 34800 | J18: 28779.6 | K18: 28779.6 | L18: 0 | M18: 31540.76 | N18: -2761.16 | O18: 1 | P18: 1.0959
A19: 23-PC-31812 | B19: On-Call: Granite Pass Mine Expansion Phase II Testing | C19: In Progress | D19: Fixed fee | E19: Cascade | F19: Jeff Spence | G19: 460600 | H19: 348674.2 | I19: 348674.2 | J19: 390957.28 | K19: 390957.28 | L19: 0 | M19: 295973.9 | N19: 94983.38 | O19: 0.757 | P19: 0.757
A20: 23-PC-31844 | B20: Task Order 37: Sea Oat Water Main Archaeological Testing | C20: Cost Tracking on Closed Project | D20: Fixed fee | E20: Cascade | F20: Jeff Spence | G20: 175300 | H20: 175300 | I20: 175300 | J20: 93481.01 | K20: 71376.84 | L20: 22104.17 | M20: 112759.17 | N20: -19278.16 | O20: 1 | P20: 1.2062
A21: 23-PC-32329 | B21: Rushgrass Draw Historic Resources Evaluation | C21: In Progress | D21: Fixed fee | E21: Chesapeake | F21: Sandy Kerr | G21: 149100 | H21: 132892.83 | I21: 132892.83 | J21: 111109.32 | K21: 111109.32 | L21: 0 | M21: 99032.78 | N21: 12076.54 | O21: 0.891 | P21: 0.8913
A22: 23-PC-32635 | B22: Rushgrass Draw Curation | C22: Cost Tracking on Closed Project | D22: Time and material | E22: Chesapeake | F22: Jason Oconnor | G22: 36800 | H22: 25024 | I22: 25024 | J22: 24644.96 | K22: 24644.96 | L22: 0 | M22: 27323.95 | N22: -2678.99 | O22: 0.68 | P22: 1.1087
A23: 23-PC-33070 | B23: Meadowlark Curation | C23: In Progress | D23: Fixed fee | E23: Front Range | F23: Reginald Vargas | G23: 55100 | H23: 46377.67 | I23: 46377.67 | J23: 34299.75 | K23: 34299.75 | L23: 0 | M23: 28871.53 | N23: 5428.22 | O23: 0.842 | P23: 0.8417
... A284: 25-PC-44140 | B284: Stone Mill Archaeological Testing | C284: In Progress | D284: Fixed fee | E284: NH Gulf | F284: Tonya Spence | G284: 149900 | H284: 149510.26 | I284: 130809.05 | J284: 100298.09 | K284: 100298.09 | L284: 0 | M284: 100035.45 | N284: 262.63733 | O284: 0.99739999 | P284: 0.99738143

Sheet Projects 90% & > $50k
D1: Summary:
D2: Removed projects with ETC>1% budget remaining
D3: Removed $0 Contract Value projects
D4: Removed previously identified ETC in final/reportingstatus
D5: Removed projects in final reporting with >10% budget remaining
D6: Total: 105
G8: Contract Value | H8: Revenue | I8: Invoiced Amount | J8: Total Revised Budget | K8: Total Budget | L8: Total Budget Adjustment | M8: Total Costs | O8: Recognized %
G9: Inception To Date | H9: Inception To Date | I9: Inception To Date | J9: Orig Budget + Adjustments | K9: Original | L9: ETC | M9: Inception To Date | N9: Inception To Date | O9: REV REC % | P9: Budget Spent %
G10: September 29, 2026 | H10: September 29, 2026 | I10: September 29, 2026 | J10: September 29, 2026 | K10: September 29, 2026 | L10: September 29, 2026 | M10: September 29, 2026 | N10: September 29, 2026 | O10: September 29, 2026
B11: Dimension name | C11: Project status | D11: Project Billing type | E11: Location Name | F11: Project Manager Name | G11: EOP | H11: Actual | I11: Actual | J11: Actual | K11: Actual | L11: Actual | M11: Actual | N11: Remaining Budget | O11: Actual | P11: Summary
A12: 23-PC-30881 | B12: Dove Canyon Mixed-Use Development Archaeological Testing | C12: Cost Tracking on Closed Project | D12: Time and material | E12: Bluegrass | F12: Alice Galloway | G12: 86200 | H12: 58616 | I12: 58616 | J12: 58650.48 | K12: 58650.48 | L12: 0 | M12: 61318.15 | N12: -2667.67 | O12: 0.68 | P12: 1.0455
A13: 23-PC-31374 | B13: Juniper Wash Canal Lining Environmental Review Support | C13: In Progress | D13: Time and material | E13: Cascade | F13: Donald Lutz | G13: 255700 | H13: 173876 | I13: 173876 | J13: 168225.03 | K13: 168225.03 | L13: 0 | M13: 202903.45 | N13: -34678.42 | O13: 0.68 | P13: 1.2061
A14: 23-PC-31844 | B14: Task Order 37: Sea Oat Water Main Archaeological Testing | C14: Cost Tracking on Closed Project | D14: Fixed fee | E14: Cascade | F14: Jeff Spence | G14: 175300 | H14: 175300 | I14: 175300 | J14: 93481.01 | K14: 71376.84 | L14: 22104.17 | M14: 112759.17 | N14: -19278.16 | O14: 1 | P14: 1.2062
A15: 23-PC-34510 | B15: Millbrook Mixed-Use Development Class III Survey | C15: Final Reporting/Review | D15: Time and material | E15: Great Lakes | F15: Geoffrey Fernandez | G15: 70000 | H15: 47600 | I15: 47600 | J15: 50246 | K15: 50246 | L15: 0 | M15: 45814.41 | N15: 4431.59 | O15: 0.68 | P15: 0.9118
A16: 23-PC-35682 | B16: Lantern Bay Class III Survey | C16: In Progress | D16: Fixed fee | E16: High Desert | F16: Eileen Poole | G16: 290400 | H16: 277361.04 | I16: 277361.04 | J16: 252938.4 | K16: 252938.4 | L16: 0 | M16: 241578.4 | N16: 11360 | O16: 0.955 | P16: 0.9551
A17: 23-PC-36063 | B17: Plover Cove Mine Expansion - Phase II Testing | C17: In Progress | D17: Fixed fee | E17: High Desert | F17: Kathy Hurley | G17: 114600 | H17: 104870.46 | I17: 104870.46 | J17: 77893.62 | K17: 77893.62 | L17: 0 | M17: 71277.07 | N17: 6616.55 | O17: 0.915 | P17: 0.9151
A18: 23-PC-36422 | B18: Hawk Point Phase I Survey | C18: In Progress | D18: Time and material | E18: Island | F18: Joan Mathis | G18: 50700 | H18: 34476 | I18: 34476 | J18: 36579.06 | K18: 32790.93 | L18: 3788.13 | M18: 37409.59 | N18: -830.53 | O18: 0.68 | P18: 1.0227
A19: 23-PC-38759 | B19: Saltgrass Cultural Resources Assessment | C19: Cost Tracking on Closed Project | D19: Time and material | E19: Red Rock | F19: Tina Aguirre | G19: 52400 | H19: 35632 | I19: 35632 | J19: 36847.68 | K19: 36847.68 | L19: 0 | M19: 40372.44 | N19: -3524.76 | O19: 0.68 | P19: 1.0957
A20: 23-PC-40537 | B20: Phase I: Tamarack Airport Apron Section 106 Consultation | C20: Lab/Curation | D20: Fixed fee | E20: Sierra | F20: Louis Huff | G20: 76500 | H20: 76500 | I20: 76500 | J20: 58746.94 | K20: 55119.6 | L20: 3627.34 | M20: 63236.56 | N20: -4489.62 | O20: 1 | P20: 1.0764
A21: 23-PC-41134 | B21: Creosote Draw Park Improvements Class III Survey | C21: In Progress | D21: Time and material | E21: Coastal Bend | F21: Steve Rubio | G21: 56300 | H21: 38284 | I21: 38284 | J21: 42714.81 | K21: 42714.81 | L21: 0 | M21: 47948.89 | N21: -5234.08 | O21: 0.68 | P21: 1.1225
A22: 23-PC-41285 | B22: Phase III: Ember Valley Park Improvements Data Recovery | C22: Cost Tracking on Closed Project | D22: Fixed fee | E22: Coastal Bend | F22: Diane Daniels | G22: 349600 | H22: 349600 | I22: 349600 | J22: 221087.04 | K22: 221087.04 | L22: 0 | M22: 229204.35 | N22: -8117.31 | O22: 1 | P22: 1.0367
A23: 23-PC-41602 | B23: Wren Hollow Cultural Resources Monitoring | C23: Lab/Curation | D23: Fixed fee | E23: Coastal Bend | F23: Alexis Nixon | G23: 755000 | H23: 705170 | I23: 705170 | J23: 444695 | K23: 444695 | L23: 0 | M23: 415325.46 | N23: 29369.54 | O23: 0.934 | P23: 0.934
... A116: 25-PC-44140 | B116: Stone Mill Archaeological Testing | C116: In Progress | D116: Fixed fee | E116: NH Gulf | F116: Tonya Spence | G116: 149900 | H116: 149510.26 | I116: 130809.05 | J116: 100298.09 | K116: 100298.09 | L116: 0 | M116: 100035.45 | N116: 262.63733 | O116: 0.99739999 | P116: 0.99738143

Sheet 100% Rev Rec FF
D1: Summary:
D2: Total: 79
G8: Contract Value | H8: Revenue | I8: Invoiced Amount | J8: Total Revised Budget | K8: Total Budget | L8: Total Budget Adjustment | M8: Total Costs | O8: Recognized %
G9: Inception To Date | H9: Inception To Date | I9: Inception To Date | J9: Orig Budget + Adjustments | K9: Original | L9: ETC | M9: Inception To Date | N9: Inception To Date | O9: REV REC % | P9: Budget Spent %
G10: September 29, 2026 | H10: September 29, 2026 | I10: September 29, 2026 | J10: September 29, 2026 | K10: September 29, 2026 | L10: September 29, 2026 | M10: September 29, 2026 | N10: September 29, 2026 | O10: September 29, 2026
B11: Dimension name | C11: Project status | D11: Project Billing type | E11: Location Name | F11: Project Manager Name | G11: EOP | H11: Actual | I11: Actual | J11: Actual | K11: Actual | L11: Actual | M11: Actual | N11: Remaining Budget | O11: Actual | P11: Summary
A12: 23-PC-31769 | B12: Rushgrass Draw Paleontological Monitoring | C12: In Progress | D12: Fixed fee | E12: Cascade | F12: Gene Nixon | G12: 34800 | H12: 34800 | I12: 34800 | J12: 28779.6 | K12: 28779.6 | L12: 0 | M12: 31540.76 | N12: -2761.16 | O12: 1 | P12: 1.0959
A13: 23-PC-31844 | B13: Task Order 37: Sea Oat Water Main Archaeological Testing | C13: Cost Tracking on Closed Project | D13: Fixed fee | E13: Cascade | F13: Jeff Spence | G13: 175300 | H13: 175300 | I13: 175300 | J13: 93481.01 | K13: 71376.84 | L13: 22104.17 | M13: 112759.17 | N13: -19278.16 | O13: 1 | P13: 1.2062
A14: 23-PC-33553 | B14: Phase III: Yarrow Point Reservoir Archaeological Testing | C14: In Progress | D14: Fixed fee | E14: Front Range | F14: Kimberly Daugherty | G14: 21600 | H14: 21600 | I14: 21600 | J14: 15245.28 | K14: 15245.28 | L14: 0 | M14: 16551.79 | N14: -1306.51 | O14: 1 | P14: 1.0857
A15: 23-PC-40537 | B15: Phase I: Tamarack Airport Apron Section 106 Consultation | C15: Lab/Curation | D15: Fixed fee | E15: Sierra | F15: Louis Huff | G15: 76500 | H15: 76500 | I15: 76500 | J15: 58746.94 | K15: 55119.6 | L15: 3627.34 | M15: 63236.56 | N15: -4489.62 | O15: 1 | P15: 1.0764
A16: 23-PC-41285 | B16: Phase III: Ember Valley Park Improvements Data Recovery | C16: Cost Tracking on Closed Project | D16: Fixed fee | E16: Coastal Bend | F16: Diane Daniels | G16: 349600 | H16: 349600 | I16: 349600 | J16: 221087.04 | K16: 221087.04 | L16: 0 | M16: 229204.35 | N16: -8117.31 | O16: 1 | P16: 1.0367
A17: 24-PC-30233 | B17: Bramble Creek Mine Expansion Phase I Survey | C17: In Progress | D17: Fixed fee | E17: Big Sky | F17: Javier Estrada | G17: 93300 | H17: 93300 | I17: 90265.16 | J17: 59544.06 | K17: 59544.06 | L17: 0 | M17: 93708.96 | N17: -34164.9 | O17: 1 | P17: 1.5738
A18: 24-PC-30679 | B18: Kestrel Butte Maritime Remote Sensing Survey | C18: In Progress | D18: Fixed fee | E18: Bluegrass | F18: Kiara Gillespie | G18: 60600 | H18: 60600 | I18: 60600 | J18: 45577.26 | K18: 45577.26 | L18: 0 | M18: 50596.88 | N18: -5019.62 | O18: 1 | P18: 1.1101
A19: 24-PC-32201 | B19: Task Order 14: Hawk Point Harbor Dredging Maritime Remote Sensing Survey | C19: In Progress | D19: Fixed fee | E19: Chesapeake | F19: Jason Oconnor | G19: 51800 | H19: 51800 | I19: 50026.67 | J19: 36731.38 | K19: 36731.38 | L19: 0 | M19: 59530.75 | N19: -22799.37 | O19: 1 | P19: 1.6207
A20: 24-PC-32647 | B20: On-Call: Granite Pass Substation Cultural Resources Monitoring | C20: Final Reporting/Review | D20: Fixed fee | E20: Chesapeake | F20: Alexandria Wilkinson | G20: 84000 | H20: 84000 | I20: 83888.35 | J20: 70198.8 | K20: 70198.8 | L20: 0 | M20: 85361.67 | N20: -15162.87 | O20: 1 | P20: 1.216
A21: 24-PC-36146 | B21: Sea Oat Bridge Replacement Phase II Testing | C21: Cost Tracking on Closed Project | D21: Fixed fee | E21: High Desert | F21: Kathy Hurley | G21: 58300 | H21: 58300 | I21: 58300 | J21: 39072.66 | K21: 39072.66 | L21: 0 | M21: 45518.79 | N21: -6446.13 | O21: 1 | P21: 1.165
A22: 24-PC-36978 | B22: Slate Ridge Water Main Archaeological Testing | C22: In Progress | D22: Fixed fee | E22: Hill Country | F22: Glen Delacruz | G22: 141000 | H22: 141000 | I22: 141000 | J22: 113970.3 | K22: 113970.3 | L22: 0 | M22: 138124.06 | N22: -24153.76 | O22: 1 | P22: 1.2119
A23: 24-PC-38486 | B23: Kestrel Butte Phase I Survey | C23: In Progress | D23: Fixed fee | E23: Red Rock | F23: Jeanette Chung | G23: 153600 | H23: 153600 | I23: 153600 | J23: 105043.81 | K23: 77500.98 | L23: 27542.83 | M23: 119866.24 | N23: -14822.43 | O23: 1 | P23: 1.1411
... A90: 26-PC-43364 | B90: Goldfinch Class III Survey | C90: Transferred Entity | D90: Fixed fee | E90: Meridian Central | F90: Raymond Hensley | G90: 24900 | H90: 24900 | I90: 23821.32 | J90: 16624.07 | K90: 15142.4 | L90: 1481.67 | M90: 22825.96 | N90: -6201.89 | O90: 1 | P90: 1.3731

Sheet Weighted Overrun Calculation
A1: PMO | B1: Project | C1: Amount | E1: PMO | F1: Overrun Amount | G1: Total Revised Budgets | H1: Weighted Overrun
A2: Meridian Central | B2: Bramble Creek Mine Expansion Archaeological Testing | C2: -89419.1 | E2: Meridian Central | F2: =SUMIF($A:$A,E2,$C:$C) | G2: =SUMIF('All Active Projects'!$E:$E,$E2,'All Active Projects'!$J:$J) | H2: =IF(G2=0,0,F2/G2)
A3: Meridian Central | B3: Riverbend Highway Widening - Phase II Testing | C3: -60264.72 | E3: Cascade | F3: =SUMIF($A:$A,E3,$C:$C) | G3: =SUMIF('All Active Projects'!$E:$E,$E3,'All Active Projects'!$J:$J) | H3: =IF(G3=0,0,F3/G3)
A4: Meridian Central | B4: Copper Flats Solar - Phase II Testing | C4: -57570.62 | E4: Red Rock | F4: =SUMIF($A:$A,E4,$C:$C) | G4: =SUMIF('All Active Projects'!$E:$E,$E4,'All Active Projects'!$J:$J) | H4: =IF(G4=0,0,F4/G4)
A5: NH Gulf (USD) | B5: Kestrel Butte Section 106 Consultation | C5: -56113.35 | E5: Chesapeake | F5: =SUMIF($A:$A,E5,$C:$C) | G5: =SUMIF('All Active Projects'!$E:$E,$E5,'All Active Projects'!$J:$J) | H5: =IF(G5=0,0,F5/G5)
A6: Cascade | B6: Riverbend GIS Mapping | C6: -53407.77 | E6: NH Gulf (USD) | F6: =SUMIF($A:$A,E6,$C:$C) | G6: =SUMIF('All Active Projects'!$E:$E,$E6,'All Active Projects'!$J:$J) | H6: =IF(G6=0,0,F6/G6)
A7: NH Gulf (USD) | B7: Cedar Hollow Airport Apron - Paleontological Monitoring | C7: -52117.269 | E7: Coastal Bend | F7: =SUMIF($A:$A,E7,$C:$C) | G7: =SUMIF('All Active Projects'!$E:$E,$E7,'All Active Projects'!$J:$J) | H7: =IF(G7=0,0,F7/G7)
A8: Coastal Bend | B8: Tamarack Levee Repair - Historic Resources Evaluation | C8: -51884.51 | E8: Great Lakes | F8: =SUMIF($A:$A,E8,$C:$C) | G8: =SUMIF('All Active Projects'!$E:$E,$E8,'All Active Projects'!$J:$J) | H8: =IF(G8=0,0,F8/G8)
A9: Lakeshore | B9: Sparrow Hill Airport Apron Phase II Testing | C9: -47180.87 | E9: Sierra | F9: =SUMIF($A:$A,E9,$C:$C) | G9: =SUMIF('All Active Projects'!$E:$E,$E9,'All Active Projects'!$J:$J) | H9: =IF(G9=0,0,F9/G9)
A10: Hill Country | B10: Yarrow Point Wastewater Plant - Phase I Survey | C10: -40602.58 | E10: Hill Country | F10: =SUMIF($A:$A,E10,$C:$C) | G10: =SUMIF('All Active Projects'!$E:$E,$E10,'All Active Projects'!$J:$J) | H10: =IF(G10=0,0,F10/G10)
A11: Red Rock | B11: Phase II: Windmill Flat Wind Farm Built Environment Survey | C11: -38645.34 | E11: Lakeshore | F11: =SUMIF($A:$A,E11,$C:$C) | G11: =SUMIF('All Active Projects'!$E:$E,$E11,'All Active Projects'!$J:$J) | H11: =IF(G11=0,0,F11/G11)
A12: Sierra | B12: Redbud Class III Survey | C12: -37807.6 | E12: Gulf Coast East | F12: =SUMIF($A:$A,E12,$C:$C) | G12: =SUMIF('All Active Projects'!$E:$E,$E12,'All Active Projects'!$J:$J) | H12: =IF(G12=0,0,F12/G12)
A13: Gulf Coast East | B13: Kestrel Butte Harbor Dredging - Historic Resources Evaluation | C13: -36999.92 | E13: Piedmont | F13: =SUMIF($A:$A,E13,$C:$C) | G13: =SUMIF('All Active Projects'!$E:$E,$E13,'All Active Projects'!$J:$J) | H13: =IF(G13=0,0,F13/G13)
... A26: Chesapeake | B26: Task Order 14: Hawk Point Harbor Dredging Maritime Remote Sensing Survey | C26: -22799.37 | E26: Paleontology | F26: =SUMIF($A:$A,E26,$C:$C) | G26: =SUMIF('All Active Projects'!$E:$E,$E26,'All Active Projects'!$J:$J) | H26: =IF(G26=0,0,F26/G26)
A27: Gulf Coast East | B27: Goldfinch Bridge Replacement Paleontological Monitoring | C27: -22368.12
A28: Chesapeake | B28: Sea Oat Airport Apron Phase II Testing | C28: -21627.63
A29: Chesapeake | B29: Timber Gap Highway Widening Paleontological Monitoring | C29: -21580.94
A30: Coastal Bend | B30: Pine Hollow Battery Storage - Archaeological Testing | C30: -21274.99
A31: Cascade | B31: Task Order 37: Sea Oat Water Main Archaeological Testing | C31: -19278.16
A32: Great Lakes | B32: Kestrel Butte Data Recovery | C32: -19277.49
A33: Red Rock | B33: On-Call: Sparrow Hill Solar Section 106 Consultation | C33: -19133.15
A34: Island | B34: Kestrel Butte Environmental Review Support | C34: -18888.91
A35: Lakeshore | B35: Falcon Mesa Archaeological Testing | C35: -18620.39
A36: Piedmont | B36: On-Call: Dove Canyon Fiber Route Cultural Resources Monitoring | C36: -18056.06
A37: Great Lakes | B37: Slate Ridge Data Recovery | C37: -17776.98
A38: Piedmont | B38: Badger Hollow Paleontological Monitoring | C38: -17514.99
... A135: Meridian Southwest | B135: Task Order 8: Pine Hollow Highway Widening Historic Resources Evaluation | C135: -7.84
